booking_mail/__init__.py
booking_mail/admin.py
booking_mail/apps.py
booking_mail/models.py
booking_mail/tests.py
booking_mail/urls.py
booking_mail/views.py
booking_mail/migrations/__init__.py
Muralikrishnan_Nambiar_booking_mail-0.1.dist-info/LICENSE
Muralikrishnan_Nambiar_booking_mail-0.1.dist-info/METADATA
Muralikrishnan_Nambiar_booking_mail-0.1.dist-info/WHEEL
Muralikrishnan_Nambiar_booking_mail-0.1.dist-info/top_level.txt
Muralikrishnan_Nambiar_booking_mail-0.1.dist-info/RECORD
